dspsim/__init__.py
dspsim/_framework.pyd
dspsim/_framework.pyi
dspsim/_library.pyd
dspsim/_library.pyi
dspsim/_util.pyd
dspsim/_util.pyi
dspsim/avril.py
dspsim/axil.py
dspsim/axis.py
dspsim/bram.py
dspsim/cmake/dspsim/dspsim-config-version.cmake
dspsim/cmake/dspsim/dspsim-config.cmake
dspsim/cmake/dspsim/dspsim-core-targets-release.cmake
dspsim/cmake/dspsim/dspsim-core-targets.cmake
dspsim/cmake/dspsim/dspsim-utils.cmake
dspsim/config.py
dspsim/cutil.py
dspsim/fifo.py
dspsim/framework.py
dspsim/FreeRTOS/License/license.txt
dspsim/FreeRTOS/links_to_doc_pages_for_the_demo_projects.url
dspsim/FreeRTOS/README.md
dspsim/FreeRTOS/Source/.gitmodules
dspsim/FreeRTOS/Source/CMakeLists.txt
dspsim/FreeRTOS/Source/croutine.c
dspsim/FreeRTOS/Source/event_groups.c
dspsim/FreeRTOS/Source/include/atomic.h
dspsim/FreeRTOS/Source/include/croutine.h
dspsim/FreeRTOS/Source/include/deprecated_definitions.h
dspsim/FreeRTOS/Source/include/event_groups.h
dspsim/FreeRTOS/Source/include/FreeRTOS.h
dspsim/FreeRTOS/Source/include/list.h
dspsim/FreeRTOS/Source/include/message_buffer.h
dspsim/FreeRTOS/Source/include/mpu_prototypes.h
dspsim/FreeRTOS/Source/include/mpu_wrappers.h
dspsim/FreeRTOS/Source/include/portable.h
dspsim/FreeRTOS/Source/include/projdefs.h
dspsim/FreeRTOS/Source/include/queue.h
dspsim/FreeRTOS/Source/include/semphr.h
dspsim/FreeRTOS/Source/include/stack_macros.h
dspsim/FreeRTOS/Source/include/StackMacros.h
dspsim/FreeRTOS/Source/include/stdint.readme
dspsim/FreeRTOS/Source/include/stream_buffer.h
dspsim/FreeRTOS/Source/include/task.h
dspsim/FreeRTOS/Source/include/timers.h
dspsim/FreeRTOS/Source/list.c
dspsim/FreeRTOS/Source/manifest.yml
dspsim/FreeRTOS/Source/portable/GCC/ARM_CM3/port.c
dspsim/FreeRTOS/Source/portable/GCC/ARM_CM3/portmacro.h
dspsim/FreeRTOS/Source/portable/MemMang/heap_1.c
dspsim/FreeRTOS/Source/portable/MemMang/heap_2.c
dspsim/FreeRTOS/Source/portable/MemMang/heap_3.c
dspsim/FreeRTOS/Source/portable/MemMang/heap_4.c
dspsim-0.3.9.dist-info/METADATA
dspsim-0.3.9.dist-info/WHEEL
dspsim-0.3.9.dist-info/entry_points.txt
dspsim-0.3.9.dist-info/licenses/LICENSE
dspsim-0.3.9.dist-info/RECORD
